powerk8s.py
powerk8s-0.8.0.dist-info/LICENSE
powerk8s-0.8.0.dist-info/METADATA
powerk8s-0.8.0.dist-info/WHEEL
powerk8s-0.8.0.dist-info/RECORD
