Metadata-Version: 2.1
Name: powerk8s
Version: 0.8.0
Summary: Powerline Segment for Kubernetes
Home-page: https://github.com/gkze/powerk8s
License: MIT
Keywords: kubernetes,powerline,tools
Author: George Kontridze
Author-email: george.kontridze@gmail.com
Requires-Python: >=3.8,<4.0
Classifier: License :: OSI Approved :: MIT License
Classifier: Programming Language :: Python :: 3
Classifier: Programming Language :: Python :: 3.8
Classifier: Programming Language :: Python :: 3.9
Classifier: Programming Language :: Python :: 3.10
Classifier: Programming Language :: Python :: 3.11
Requires-Dist: PyYAML (>=6.0,<7.0)
Requires-Dist: kubernetes (>=26.1,<27.0)
Requires-Dist: powerline-status (>=2.7,<3.0)
Project-URL: Documentation, https://gkze.github.io/powerk8s/powerk8s.html
Project-URL: Repository, https://github.com/gkze/powerk8s
